greater_than/greater_than.v
module greater_than (
    A, B, F
);

input [1:0] A, B;
output F;

// assign F = A > B;

assign F = A[1] & ~B[1] | A[0] & ~B[1] & ~B[0] | A[1] & A[0] & ~B[0];
    
endmodule

.history/greater_than/greater_than_tb_20240422112603.v
`timescale 1ps/1ps
`include "greater_than.v"

module greater_than_tb;

reg[1:0] A,B;
wire F;

greater_than_uut(A, B, F);

initial begin
    {A, B} = 4'd0; #20;
end
endmodule

greater_than/greater_than_tb.vcd
$date
	Mon Apr 22 11:42:19 2024
$end
$version
	Icarus Verilog
$end
$timescale
	1ps
$end
$scope module greater_than_tb $end
$var wire 1 ! F $end
$var reg 2 " A [1:0] $end
$var reg 2 # B [1:0] $end
$scope module uut $end
$var wire 2 $ A [1:0] $end
$var wire 2 % B [1:0] $end
$var wire 1 ! F $end
$upscope $end
$upscope $end
$enddefinitions $end
$comment Show the parameter values. $end
$dumpall
$end
#0
$dumpvars
b0 %
b0 $
b0 #
b0 "
0!
$end
#20
b1 #
b1 %
#40
b10 #
b10 %
#60
b11 #
b11 %
#80
1!
b1 "
b1 $
b0 #
b0 %
#100
0!
b1 #
b1 %
#120
0!
b10 #
b10 %
#140
b11 #
b11 %
#160
1!
b10 "
b10 $
b0 #
b0 %
#180
b1 #
b1 %
#200
0!
b10 #
b10 %
#220
b11 #
b11 %
#240
1!
b11 "
b11 $
b0 #
b0 %
#260
b1 #
b1 %
#280
b10 #
b10 %
#300
0!
b11 #
b11 %
